odoo/addons/repair_scrap/README.rst
odoo/addons/repair_scrap/__init__.py
odoo/addons/repair_scrap/__manifest__.py
odoo/addons/repair_scrap/i18n/repair_scrap.pot
odoo/addons/repair_scrap/models/__init__.py
odoo/addons/repair_scrap/models/repair_order.py
odoo/addons/repair_scrap/models/repair_type.py
odoo/addons/repair_scrap/models/stock_move.py
odoo/addons/repair_scrap/models/stock_rule.py
odoo/addons/repair_scrap/models/stock_scrap.py
odoo/addons/repair_scrap/readme/CONTRIBUTORS.rst
odoo/addons/repair_scrap/readme/DESCRIPTION.rst
odoo/addons/repair_scrap/security/ir.model.access.csv
odoo/addons/repair_scrap/static/description/icon.png
odoo/addons/repair_scrap/static/description/index.html
odoo/addons/repair_scrap/tests/__init__.py
odoo/addons/repair_scrap/tests/test_repair_scrap.py
odoo/addons/repair_scrap/views/repair_order_view.xml
odoo/addons/repair_scrap/views/repair_type_views.xml
odoo/addons/repair_scrap/views/stock_scrap_view.xml
odoo/addons/repair_scrap/wizards/__init__.py
odoo/addons/repair_scrap/wizards/repair_make_scrap.py
odoo/addons/repair_scrap/wizards/repair_scrap_view.xml
odoo_addon_repair_scrap-15.0.1.1.0.dist-info/METADATA
odoo_addon_repair_scrap-15.0.1.1.0.dist-info/WHEEL
odoo_addon_repair_scrap-15.0.1.1.0.dist-info/top_level.txt
odoo_addon_repair_scrap-15.0.1.1.0.dist-info/RECORD
