Metadata-Version: 2.1
Name: odoo-addon-repair_scrap
Version: 15.0.1.1.0
Summary: To send to scrap components or irreparable components.
Home-page: https://github.com/OCA/repair
Author: ForgeFlow, Odoo Community Association (OCA)
Author-email: support@odoo-community.org
License: AGPL-3
Classifier: Programming Language :: Python
Classifier: Framework :: Odoo
Classifier: Framework :: Odoo :: 15.0
Classifier: License :: OSI Approved :: GNU Affero General Public License v3
Classifier: Development Status :: 3 - Alpha
Requires-Python: >=3.8
Requires-Dist: odoo-addon-repair-type <15.1dev,>=15.0dev
Requires-Dist: odoo <15.1dev,>=15.0a
